elite/__init__.py
elite/_baseec.py
elite/_ec.py
elite/_info.py
elite/_kinematics.py
elite/_monitor.py
elite/_move.py
elite/_moveml.py
elite/_movett.py
elite/_profinet.py
elite/_servo.py
elite/_var.py
elirobots-0.0.7.dist-info/METADATA
elirobots-0.0.7.dist-info/WHEEL
elirobots-0.0.7.dist-info/top_level.txt
elirobots-0.0.7.dist-info/RECORD
