Metadata-Version: 2.1
Name: elirobots
Version: 0.0.7
Summary: a SDK library for Elite EC Series Robot 
Home-page: https://github.com/JunJie-zhang-o/eliterobot.git
Author: Elite
Author-email: zhangjunjie@elibot.cn
License: UNKNOWN
Keywords: elite,elibot,eliterobot,robot,Robot,robotSDK
Platform: UNKNOWN
Requires-Dist: loguru (==0.6.0)
